exccpkg/__init__.py
exccpkg/exccpkg.py
exccpkg/tools.py
exccpkg-3.0.3.dist-info/licenses/LICENSE
exccpkg-3.0.3.dist-info/METADATA
exccpkg-3.0.3.dist-info/WHEEL
exccpkg-3.0.3.dist-info/top_level.txt
exccpkg-3.0.3.dist-info/RECORD
