Metadata-Version: 2.4
Name: exccpkg
Version: 3.0.3
Summary: An explicit C++ package builder.
Author: AdjWang
Author-email: wwang230513@gmail.com
Requires-Python: >=3.12
License-File: LICENSE
Requires-Dist: requests
Dynamic: author
Dynamic: author-email
Dynamic: license-file
Dynamic: requires-dist
Dynamic: requires-python
Dynamic: summary
